<pb n="447"/>
IN DIOSCORIDEM. II. 81—86. 447
<lb/>bet sequaces.<ref target="#fn91">91</ref> Nihilominus, si <foreign xml:lang="grc">δορκάς</foreign> a <foreign xml:lang="grc">δέρκειν</foreign> nomen
<lb/>habet, alii fere nulli animali tam apta haec appellatio
<lb/>est, quam Antilopi ii, cuius oculi formosissimi et visus
<lb/>acutissimus dicuntur. Haec Syriam habitat et Asiae mi-
<lb/>noris regiones, quae Notum spectant, sed in Lycia non
<lb/>transire eam montes Syris vicinos, Plinius perhibet.<ref target="#fn92">92</ref>
<lb/>Aristoteli quidem et capreolus <foreign xml:lang="grc">δορκάς</foreign> dicitur, sed serio-
<lb/>ribus temporibus hac ratione distincta fuisse animalia, ut
<lb/><foreign xml:lang="grc">δόρκος</foreign> capreolus, <foreign xml:lang="grc">δορκάς</foreign> vero sola antilope vocaretur,
<lb/>probabile est. In qua sententia si fallor, <foreign xml:lang="grc">χαλεπὸν οἶμαι</foreign>
<lb/><foreign xml:lang="grc">σὺν Γαληνῷ, ἄνθρωπον ὄντα, μὴ διαμαρτάνειν ἐν πολλοῖς.</foreign>
<lb/><foreign xml:lang="grc">Βούβαλος</foreign> est <hi rend="italic">Antilope Bubalis</hi>, quae Africam borea-
<lb/>lem habitat.<ref target="#fn93">93</ref>
<lb/>Cap. LXXXVI. <foreign xml:lang="grc">Βίκος</foreign> et <foreign xml:lang="grc">βικίον</foreign> peregrina habentur
<lb/>nomina, imo cum ebraeo <foreign xml:lang="he">בַּקְבּוּק</foreign> componuntur, pro quo
<lb/>LXX interpretes posuerunt.<ref target="#fn94">94</ref> <foreign xml:lang="grc">Βίκος</foreign> tamen, <foreign xml:lang="grc">στάμνος ὦτα</foreign>
<lb/><foreign xml:lang="grc">ἔχων</foreign> Hesychio, antiqua vox est, qua iam Herodotus
<lb/>utitur.<ref target="#fn95">95</ref>
<lb/>Cap. LXXXVI. <foreign xml:lang="grc">Καλλιώνυμος</foreign> est piscis, mari me-
<lb/>diterraneo satis communis, <hi rend="italic">Uranoscopus scaber</hi>, cuius
<lb/>grandem vesicam felleam iam Aristoteles praedicat.<ref target="#fn96">96</ref>
<lb/>Esse autem eumdem cum <foreign xml:lang="grc">οὐρανοσκόπῳ</foreign>, inde iam Ronde-
<lb/>letius<ref target="#fn97">97</ref>, Schneiderus<ref target="#fn98">98</ref> et Coray<ref target="#fn99">99</ref> effecerunt, quod Di-
<lb/>philus Siphnius apud Athenaeum<ref target="#fn100">100</ref> dicat: <foreign xml:lang="grc">Οὐρανοσκόπος</foreign>
<lb/><foreign xml:lang="grc">δὲ, ὁ καὶ ἄγνος καλούμενος, ἢ καὶ καλλιώνυμος, βαρύς.</foreign>
<lb/>Legimus vero: <foreign xml:lang="grc">Οὐρ. δὲ, καὶ ὁ ἄγν. καλ., ἢ κ. καλλ., βα-</foreign>
<lb/>
<note xml:id="fn91" n="91" place="foot">Hieroz. 1. p. 966.</note>
<note xml:id="fn92" n="92" place="foot">Plin. 8, 83. Cum Lycia nullo modo Syriae sit contermina,
<lb/>Ciliciam substituendam esse Harduinus suadet. Possene tamen So-
<lb break="no"/>lymorum Pisidiae natio, quae interiisse iam Eratostheni dicebatur
<lb/>(Plin. 5, 33.) intelligi? Namque et Syros et Phoenices ultra Ama-
<lb/>num et Taurum montem antiquitus immigrasse, et Solymos Pisidiae
<lb/>punice loquutos fuisse, traditur. (Ioseph. antiqu. iud. 1, 7. contra
<lb/>Ap. 1, 12.)</note>
<note xml:id="fn93" n="93" place="foot"><foreign xml:lang="grc">Ζορκάδες καὶ βουβάλιες ἐν Λιβύῃ.</foreign> Herod. 4, 192. <foreign xml:lang="grc">Ζόρκες</foreign>
<lb/>Straboni dicuntur lib. 12. p. 76.</note>
<note xml:id="fn94" n="94" place="foot">Ierem. 19, 1.</note>
<note xml:id="fn95" n="95" place="foot">Herod. 1, 194.</note>
<note xml:id="fn96" n="96" place="foot">Hist. anim. 2, 11. Aelian. hist. anim. 13, 4.</note>
<note xml:id="fn97" n="97" place="foot">Apud Gesner. de pisc. p. 138.</note>
<note xml:id="fn98" n="98" place="foot">Exc. 2. ad Aelian. p. 573.</note>
<note xml:id="fn99" n="99" place="foot">Ad Xenocr. de aquatil. p. 68.</note>
<note xml:id="fn100" n="100" place="foot">Lib. 8. c. 52.</note>
